onginred/service.py
onginred/config.py
onginred/triggers.py
onginred/behavior.py
onginred/protocols.py
onginred/cron.py
onginred/__init__.py
onginred/builder.py
onginred/cli.py
onginred/utils.py
onginred/file_io.py
onginred/sockets.py
onginred/errors.py
onginred/schedule.py
onginred/launchctl.py
onginred-0.1.0.dist-info/WHEEL
onginred-0.1.0.dist-info/entry_points.txt
onginred-0.1.0.dist-info/METADATA
onginred-0.1.0.dist-info/RECORD
