Metadata-Version: 2.3
Name: onginred
Version: 0.1.0
Summary: manager for macos launchd services
Author: Joseph M Courtney
Author-email: Joseph M Courtney <Joseph.M.Courtney@gmail.com>
License: GPL-3.0-only
Classifier: Development Status :: 3 - Alpha
Classifier: License :: OSI Approved :: GNU General Public License (GPL)
Classifier: Programming Language :: Python :: 3
Classifier: Operating System :: OS Independent
Requires-Dist: croniter>=6.0.0
Requires-Dist: pydantic>=2.11.7
Requires-Python: >=3.13
Project-URL: Bug Tracker, https://github.com/josephcourtney/onginred/issues
Project-URL: Homepage, https://github.com/josephcourtney/onginred
